{
  "full_summary": "C/C++ file with ~19 functions. Handles low level operations or hardware interfaces typical for embedded systems in stmpe1600.",
  "chunks": [
    {
      "content": "/**\n  ******************************************************************************\n  * @file    stmpe1600.c\n  * @author  MCD Application Team\n  * @brief   This file provides a set of functions needed to manage the STMPE1600\n  *          IO Expander devices.\n  ******************************************************************************\n  * @attention\n  *\n  * Copyright (c) 2015 STMicroelectronics.\n  * All rights reserved.\n  *\n  * This software is licensed under terms that can be found in the LICENSE file\n  * in the root directory of this software component.\n  * If no LICENSE file comes with this software, it is provided AS-IS.\n  *\n  ******************************************************************************\n  */\n\n/* Includes ------------------------------------------------------------------*/\n#include \"stmpe1600.h\"\n\n/** @addtogroup BSP\n  * @{\n  */\n\n/** @addtogroup Components\n  * @{\n  */\n\n/** @defgroup STMPE1600\n  * @{\n  */\n\n/* Private typedef -----------------------------------------------------------*/\n\n/** @defgroup STMPE1600_Private_Types_Definitions\n  * @{\n  */\n\n/* Private define ------------------------------------------------------------*/\n\n/** @defgroup STMPE1600_Private_Defines\n  * @{\n  */\n#define STMPE1600_MAX_INSTANCE        2\n\n/* Private macro -------------------------------------------------------------*/\n\n/** @defgroup STMPE1600_Private_Macros\n  * @{\n  */\n\n/* Private variables ---------------------------------------------------------*/\nstatic uint16_t tmp = 0;\n\n/** @defgroup STMPE1600_Private_Variables\n  * @{\n  */\n/* IO driver structure initialization */\nIO_DrvTypeDef stmpe1600_io_drv =\n{\n  stmpe1600_Init,\n  stmpe1600_ReadID,\n  stmpe1600_Reset,\n  stmpe1600_Start,\n  stmpe1600_IO_Config,\n  stmpe1600_IO_WritePin,\n  stmpe1600_IO_ReadPin,\n  0,\n  0,\n  stmpe1600_IO_ITStatus,\n  stmpe1600_IO_ClearIT,\n};\n\nuint8_t stmpe1600[STMPE1600_MAX_INSTANCE] = {0};\n/**\n  * @}\n  */\n\n/* Private function prototypes -----------------------------------------------*/\n\n/** @defgroup STMPE1600_Private_Function_Prototypes\n  * @{\n  */\nstatic uint8_t stmpe1600_GetInstance(uint16_t DeviceAddr);\n\n/* Private functions ---------------------------------------------------------*/\n\n/** @defgroup STMPE1600_Private_Functions\n  * @{\n  */\n\n/**\n  * @brief  Initialize the stmpe1600 and configure the needed hardware resources\n  * @param  DeviceAddr: Device address on communication Bus.\n  * @retval None\n  */\nvoid stmpe1600_Init(uint16_t DeviceAddr)\n{",
      "metadata": {
        "start_line": 1,
        "lang": "c",
        "desc": "Code chunk from EcoflowSTM32F4/lib/bsp/Components/stmpe1600/stmpe1600.c lines 1-100"
      },
      "id": "EcoflowSTM32F4/lib/bsp/Components/stmpe1600/stmpe1600.c:chunk0"
    },
    {
      "content": "  uint8_t instance;\n  uint8_t empty;\n\n  /* Check if device instance already exists */\n  instance = stmpe1600_GetInstance(DeviceAddr);\n\n  if(instance == 0xFF)\n  {\n    /* Look for empty instance */\n    empty = stmpe1600_GetInstance(0);\n\n    if(empty < STMPE1600_MAX_INSTANCE)\n    {\n      /* Register the current device instance */\n      stmpe1600[empty] = DeviceAddr;\n\n      /* Initialize IO BUS layer */\n      IOE_Init();\n\n      /* Generate stmpe1600 Software reset */\n      stmpe1600_Reset(DeviceAddr);\n    }\n  }\n}\n\n/**\n  * @brief  Configures the touch Screen Controller (Single point detection)\n  * @param  DeviceAddr: Device address on communication Bus.\n  * @retval None.\n  */\nvoid stmpe1600_Start(uint16_t DeviceAddr, uint32_t IO_Pin)\n{\n  /*Configuration already done during the initialization */\n}\n\n/**\n  * @brief  Reset the stmpe1600 by Software.\n  * @param  DeviceAddr: Device address on communication Bus.\n  * @retval None\n  */\nvoid stmpe1600_Reset(uint16_t DeviceAddr)\n{\n  /* Power Down the stmpe1600 */\n  IOE_Write(DeviceAddr, STMPE1600_REG_SYS_CTRL, (uint16_t)0x80);\n\n  /* Wait for a delay to ensure registers erasing */\n  IOE_Delay(2);\n\n  /* Power On the Codec after the power off: all registers are reinitialized */\n  IOE_Write(DeviceAddr, STMPE1600_REG_SYS_CTRL, (uint16_t)0x00);\n\n  /* Wait for a delay to ensure registers erasing */\n  IOE_Delay(2);\n}\n\n/**\n  * @brief  Read the stmpe1600 device ID.\n  * @param  DeviceAddr: Device address on communication Bus.\n  * @retval The Device ID (two bytes).\n  */\nuint16_t stmpe1600_ReadID(uint16_t DeviceAddr)\n{\n  uint8_t tmpData[2] = {0 , 0};\n\n  /* Initialize IO BUS layer */\n  IOE_Init();\n\n  /* Read the stmpe1600 device ID */\n  IOE_ReadMultiple(DeviceAddr, STMPE1600_REG_CHP_ID, tmpData, 2);\n\n  /* Return the device ID value */\n  return((uint16_t)tmpData[0] | (((uint16_t)tmpData[1]) << 8));\n}\n\n/**\n  * @brief  Set the global interrupt Polarity.\n  * @param  DeviceAddr: Device address on communication Bus.\n  * @param  Polarity: could be one of these values;\n  *   @arg  STMPE1600_POLARITY_LOW: Interrupt line is active Low/Falling edge\n  *   @arg  STMPE1600_POLARITY_HIGH: Interrupt line is active High/Rising edge\n  * @retval None\n  */\nvoid stmpe1600_SetITPolarity(uint16_t DeviceAddr, uint8_t Polarity)\n{\n  uint8_t tmp = 0;\n\n  /* Get the current register value */\n  tmp = IOE_Read(DeviceAddr, STMPE1600_REG_SYS_CTRL);\n\n  /* Mask the polarity bit */\n  tmp &= ~(uint16_t)0x01;\n\n  /* Set the Interrupt Output line polarity */\n  tmp |= (uint8_t)Polarity;\n\n  /* Set the new register value */\n  IOE_Write(DeviceAddr, STMPE1600_REG_SYS_CTRL, tmp);\n}\n\n/**",
      "metadata": {
        "start_line": 101,
        "lang": "c",
        "desc": "Code chunk from EcoflowSTM32F4/lib/bsp/Components/stmpe1600/stmpe1600.c lines 101-200"
      },
      "id": "EcoflowSTM32F4/lib/bsp/Components/stmpe1600/stmpe1600.c:chunk1"
    },
    {
      "content": "  * @brief  Enable the Global interrupt.\n  * @param  DeviceAddr: Device address on communication Bus.\n  * @retval None\n  */\nvoid stmpe1600_EnableGlobalIT(uint16_t DeviceAddr)\n{\n  uint8_t tmpData[2] = {0 , 0};\n\n  /* Configure NVIC IT for IOE */\n  IOE_ITConfig();\n\n  /* Get the current register value */\n  IOE_ReadMultiple(DeviceAddr, STMPE1600_REG_SYS_CTRL, tmpData, 2);\n\n  tmp = ((uint16_t)tmpData[0] | (((uint16_t)tmpData[1]) << 8));\n\n  /* Set the global interrupts to be Enabled */\n  tmp |= (uint16_t)STMPE1600_IT_ENABLE;\n\n  /* Write Back the Interrupt Control register */\n  IOE_WriteMultiple(DeviceAddr, STMPE1600_REG_SYS_CTRL, (uint8_t *)&tmp, 2);\n}\n\n/**\n  * @brief  Disable the Global interrupt.\n  * @param  DeviceAddr: Device address on communication Bus.\n  * @retval None\n  */\nvoid stmpe1600_DisableGlobalIT(uint16_t DeviceAddr)\n{\n  uint8_t tmpData[2] = {0 , 0};\n\n  /* Get the current register value */\n  IOE_ReadMultiple(DeviceAddr, STMPE1600_REG_SYS_CTRL, tmpData, 2);\n\n  tmp = ((uint16_t)tmpData[0] | (((uint16_t)tmpData[1]) << 8));\n\n  /* Set the global interrupts to be Enabled */\n  tmp &= ~(uint16_t)STMPE1600_IT_ENABLE;\n\n  /* Write Back the Interrupt Control register */\n  IOE_WriteMultiple(DeviceAddr, STMPE1600_REG_SYS_CTRL, (uint8_t *)&tmp, 2);\n}\n\n/**\n  * @brief  Initialize the selected pin(s) direction.\n  * @param  DeviceAddr: Device address on communication Bus.\n  * @param  IO_Pin: IO pin(s) to be configured.\n  *         This parameter could be any combination of the following values:\n  *   @arg  STMPE1600_PIN_x: where x can be from 0 to 15.\n  * @param  Direction: could be STMPE1600_DIRECTION_IN or STMPE1600_DIRECTION_OUT.\n  * @retval None\n  */\nvoid stmpe1600_IO_InitPin(uint16_t DeviceAddr, uint32_t IO_Pin, uint8_t Direction)\n{\n  uint8_t tmpData[2] = {0 , 0};\n\n  /* Get the current register value */\n  IOE_ReadMultiple(DeviceAddr, STMPE1600_REG_GPDR, tmpData, 2);\n\n  tmp = ((uint16_t)tmpData[0] | (((uint16_t)tmpData[1]) << 8));\n\n  /* Set the Pin direction */\n  if (Direction != STMPE1600_DIRECTION_IN)\n  {\n    tmp |= (uint16_t)IO_Pin;\n  }\n  else\n  {\n    tmp &= ~(uint16_t)IO_Pin;\n  }\n\n  /* Set the new register value */\n  IOE_WriteMultiple(DeviceAddr, STMPE1600_REG_GPDR, (uint8_t *)&tmp, 2);\n}\n\n/**\n  * @brief  Configure the IO pin(s) according to IO mode structure value.\n  * @param  DeviceAddr: Device address on communication Bus.\n  * @param  IO_Pin: The output pin to be set or reset. This parameter can be one\n  *         of the following values:\n  *   @arg  STMPE1600_PIN_x: where x can be from 0 to 7.\n  * @param  IO_Mode: The IO pin mode to configure, could be one of the following values:\n  *   @arg  IO_MODE_INPUT\n  *   @arg  IO_MODE_OUTPUT\n  *   @arg  IO_MODE_IT_RISING_EDGE\n  *   @arg  IO_MODE_IT_FALLING_EDGE\n  * @retval 0 if no error, IO_Mode if error\n  */\nuint8_t stmpe1600_IO_Config(uint16_t DeviceAddr, uint32_t IO_Pin, IO_ModeTypedef IO_Mode)\n{\n  uint8_t error_code = 0;\n    uint8_t buffer[2] = {0,0};\n\n  /* Configure IO pin according to selected IO mode */\n  switch(IO_Mode)\n  {\n  case IO_MODE_INPUT: /* Input mode */\n    stmpe1600_IO_DisablePinIT(DeviceAddr, IO_Pin);\n    stmpe1600_IO_InitPin(DeviceAddr, IO_Pin, STMPE1600_DIRECTION_IN);",
      "metadata": {
        "start_line": 201,
        "lang": "c",
        "desc": "Code chunk from EcoflowSTM32F4/lib/bsp/Components/stmpe1600/stmpe1600.c lines 201-300"
      },
      "id": "EcoflowSTM32F4/lib/bsp/Components/stmpe1600/stmpe1600.c:chunk2"
    },
    {
      "content": "    break;\n\n  case IO_MODE_OUTPUT: /* Output mode */\n    stmpe1600_IO_DisablePinIT(DeviceAddr, IO_Pin);\n    stmpe1600_IO_InitPin(DeviceAddr, IO_Pin, STMPE1600_DIRECTION_OUT);\n    break;\n\n  case IO_MODE_IT_RISING_EDGE: /* Interrupt rising edge mode */\n    stmpe1600_SetITPolarity(DeviceAddr, STMPE1600_POLARITY_HIGH);\n    stmpe1600_IO_EnablePinIT(DeviceAddr, IO_Pin);\n    stmpe1600_IO_InitPin(DeviceAddr, IO_Pin, STMPE1600_DIRECTION_IN);\n    /* Clear all IO IT pending bits if any */\n    stmpe1600_IO_ClearIT(DeviceAddr, IO_Pin);\n\n    /* Read GMPR to enable interrupt */\n    IOE_ReadMultiple(DeviceAddr , STMPE1600_REG_GPMR, buffer, 2);\n    break;\n\n  case IO_MODE_IT_FALLING_EDGE: /* Interrupt falling edge mode */\n    stmpe1600_SetITPolarity(DeviceAddr, STMPE1600_POLARITY_LOW);\n    stmpe1600_IO_EnablePinIT(DeviceAddr, IO_Pin);\n    stmpe1600_IO_InitPin(DeviceAddr, IO_Pin, STMPE1600_DIRECTION_IN);\n\n    /* Clear all IO IT pending bits if any */\n    stmpe1600_IO_ClearIT(DeviceAddr, IO_Pin);\n\n    /* Read GMPR to enable interrupt */\n    IOE_ReadMultiple(DeviceAddr , STMPE1600_REG_GPMR, buffer, 2);\n    break;\n\n  default:\n    error_code = (uint8_t) IO_Mode;\n\tbreak;\n  }\n  return error_code;\n}\n\n/**\n  * @brief  Enable polarity inversion of the selected IO pin(s).\n  * @param  DeviceAddr: Device address on communication Bus.\n  * @param  IO_Pin: IO pin(s) to be configured.\n  *         This parameter could be any combination of the following values:\n  *   @arg  STMPE1600_PIN_x: where x can be from 0 to 15.\n  * @retval None\n  */\nvoid stmpe1600_IO_PolarityInv_Enable(uint16_t DeviceAddr, uint32_t IO_Pin)\n{\n  uint8_t tmpData[2] = {0 , 0};\n\n  /* Get the current register value */\n  IOE_ReadMultiple(DeviceAddr, STMPE1600_REG_GPPIR, tmpData, 2);\n\n  tmp = ((uint16_t)tmpData[0] | (((uint16_t)tmpData[1]) << 8));\n\n  /* Enable pin polarity inversion */\n  tmp |= (uint16_t)IO_Pin;\n\n  /* Set the new register value */\n  IOE_WriteMultiple(DeviceAddr, STMPE1600_REG_GPPIR, (uint8_t *)&tmp, 2);\n}\n\n/**\n  * @brief  Disable polarity inversion of the selected IO pins.\n  * @param  DeviceAddr: Device address on communication Bus.\n  * @param  IO_Pin: IO pin(s) to be configured.\n  *         This parameter could be any combination of the following values:\n  *   @arg  STMPE1600_PIN_x: where x can be from 0 to 15.\n  * @retval None\n  */\nvoid stmpe1600_IO_PolarityInv_Disable(uint16_t DeviceAddr, uint32_t IO_Pin)\n{\n  uint8_t tmpData[2] = {0 , 0};\n\n  /* Get the current register value */\n  IOE_ReadMultiple(DeviceAddr, STMPE1600_REG_GPPIR, tmpData, 2);\n\n  tmp = ((uint16_t)tmpData[0] | (((uint16_t)tmpData[1]) << 8));\n\n  /* Disable pin polarity inversion */\n   tmp &= ~ (uint16_t)IO_Pin;\n\n  /* Set the new register value */\n  IOE_WriteMultiple(DeviceAddr, STMPE1600_REG_GPPIR, (uint8_t *)&tmp, 2);\n}\n\n/**\n  * @brief  Set the value of the selected IO pins.\n  * @param  DeviceAddr: Device address on communication Bus.\n  * @param  IO_Pin: IO pin(s) to be set.\n  *         This parameter could be any combination of the following values:\n  *   @arg  STMPE1600_PIN_x: where x can be from 0 to 15.\n  * @param  PinState: The value to be set.\n  * @retval None\n  */\nvoid stmpe1600_IO_WritePin(uint16_t DeviceAddr, uint32_t IO_Pin, uint8_t PinState)\n{\n  uint8_t tmpData[2] = {0 , 0};\n\n  /* Get the current register value */\n  IOE_ReadMultiple(DeviceAddr, STMPE1600_REG_GPMR, tmpData, 2);",
      "metadata": {
        "start_line": 301,
        "lang": "c",
        "desc": "Code chunk from EcoflowSTM32F4/lib/bsp/Components/stmpe1600/stmpe1600.c lines 301-400"
      },
      "id": "EcoflowSTM32F4/lib/bsp/Components/stmpe1600/stmpe1600.c:chunk3"
    },
    {
      "content": "\n  tmp = ((uint16_t)tmpData[0] | (((uint16_t)tmpData[1]) << 8));\n\n  /* Set the pin state */\n  if(PinState != 0)\n  {\n    tmp |= (uint16_t)IO_Pin;\n  }\n  else\n  {\n    tmp &= ~(uint16_t)IO_Pin;\n  }\n\n  /* Set the new register value */\n  IOE_WriteMultiple(DeviceAddr, STMPE1600_REG_GPSR, (uint8_t *)&tmp, 2);\n}\n\n/**\n  * @brief  Read the state of the selected IO pin(s).\n  * @param  DeviceAddr: Device address on communication Bus.\n  * @param  IO_Pin: IO pin(s) to be read.\n  *         This parameter could be any combination of the following values:\n  *   @arg  STMPE1600_PIN_x: where x can be from 0 to 15.\n  * @retval State of the selected IO pin(s).\n  */\nuint32_t stmpe1600_IO_ReadPin(uint16_t DeviceAddr, uint32_t IO_Pin)\n{\n  uint8_t tmpData[2] = {0 , 0};\n\n  /* Get the register value */\n  IOE_ReadMultiple(DeviceAddr, STMPE1600_REG_GPMR, tmpData, 2);\n\n  tmp = ((uint16_t)tmpData[0] | (((uint16_t)tmpData[1]) << 8));\n\n  /* Return the pin(s) state */\n  return(tmp & IO_Pin);\n}\n\n/**\n  * @brief  Enable the interrupt mode for the selected IO pin(s).\n  * @param  DeviceAddr: Device address on communication Bus.\n  * @param  IO_Pin: IO pin(s) to be configured.\n  *         This parameter could be any combination of the following values:\n  *   @arg  STMPE1600_PIN_x: where x can be from 0 to 15.\n  * @retval None\n  */\nvoid stmpe1600_IO_EnablePinIT(uint16_t DeviceAddr, uint32_t IO_Pin)\n{\n  uint8_t tmpData[2] = {0 , 0};\n\n  /* Enable global interrupt */\n  stmpe1600_EnableGlobalIT(DeviceAddr);\n\n  /* Get the current register value */\n  IOE_ReadMultiple(DeviceAddr, STMPE1600_REG_IEGPIOR, tmpData, 2);\n\n  tmp = ((uint16_t)tmpData[0] | (((uint16_t)tmpData[1]) << 8));\n\n  /* Put pin in IT mode */\n  tmp |= (uint16_t)IO_Pin;\n\n  /* Write the new register value */\n  IOE_WriteMultiple(DeviceAddr, STMPE1600_REG_IEGPIOR, (uint8_t *)&tmp, 2);\n}\n\n/**\n  * @brief  Disable the interrupt mode for the selected IO pin(s).\n  * @param  DeviceAddr: Device address on communication Bus.\n  * @param  IO_Pin: IO pin(s) to be configured.\n  *         This parameter could be any combination of the following values:\n  *   @arg  STMPE1600_PIN_x: where x can be from 0 to 15.\n  * @retval None\n  */\nvoid stmpe1600_IO_DisablePinIT(uint16_t DeviceAddr, uint32_t IO_Pin)\n{\n  uint8_t tmpData[2] = {0 , 0};\n\n  /* Get the current register value */\n  IOE_ReadMultiple(DeviceAddr, STMPE1600_REG_IEGPIOR, tmpData, 2);\n\n  tmp = ((uint16_t)tmpData[0] | (((uint16_t)tmpData[1]) << 8));\n\n  /* Disable the IT pin mode */\n  tmp &= ~(uint16_t)IO_Pin;\n\n  /* Set the new register value */\n  IOE_WriteMultiple(DeviceAddr, STMPE1600_REG_IEGPIOR, (uint8_t *)&tmp, 2);\n}\n\n/**\n  * @brief  Read the IT status of the selected IO pin(s)\n  *         (clears all the pending bits if any).\n  * @param  DeviceAddr: Device address on communication Bus.\n  * @param  IO_Pin: IO pin(s) to be checked.\n  *         This parameter could be any combination of the following values:\n  *   @arg  STMPE1600_PIN_x: where x can be from 0 to 15.\n  * @retval IT Status of the selected IO pin(s).\n  */\nuint32_t stmpe1600_IO_ITStatus(uint16_t DeviceAddr, uint32_t IO_Pin)\n{",
      "metadata": {
        "start_line": 401,
        "lang": "c",
        "desc": "Code chunk from EcoflowSTM32F4/lib/bsp/Components/stmpe1600/stmpe1600.c lines 401-500"
      },
      "id": "EcoflowSTM32F4/lib/bsp/Components/stmpe1600/stmpe1600.c:chunk4"
    },
    {
      "content": "  uint8_t tmpData[2] = {0 , 0};\n\n  /* Get the register value */\n  IOE_ReadMultiple(DeviceAddr, STMPE1600_REG_ISGPIOR, tmpData, 2);\n\n  tmp = ((uint16_t)tmpData[0] | (((uint16_t)tmpData[1]) << 8));\n\n  /* Return the pin IT status */\n  return((tmp & IO_Pin) == IO_Pin);\n}\n\n/**\n  * @brief  Detect an IT pending bit from the selected IO pin(s).\n  *         (clears all the pending bits if any).\n  * @param  DeviceAddr: Device address on communication Bus.\n  * @param  IO_Pin: IO pin(s) to be checked.\n  *         This parameter could be any combination of the following values:\n  *   @arg  STMPE1600_PIN_x: where x can be from 0 to 15.\n  * @retval IT pending bit detection status.\n  */\nuint8_t stmpe1600_IO_ReadIT(uint16_t DeviceAddr, uint32_t IO_Pin)\n{\n  uint8_t tmpData[2] = {0 , 0};\n\n  /* Get the register value */\n  IOE_ReadMultiple(DeviceAddr, STMPE1600_REG_ISGPIOR, tmpData, 2);\n\n  tmp = ((uint16_t)tmpData[0] | (((uint16_t)tmpData[1]) << 8));\n\n  /* Return if there is an IT pending bit or not */\n  return(tmp & IO_Pin);\n}\n\n/**\n  * @brief  Clear all the IT pending bits if any.\n  * @param  DeviceAddr: Device address on communication Bus.\n  * @retval None\n  */\nvoid stmpe1600_IO_ClearIT(uint16_t DeviceAddr, uint32_t IO_Pin)\n{\n  uint8_t tmpData[2] = {0 , 0};\n\n  /* Get the register value to clear all pending bits */\n  IOE_ReadMultiple(DeviceAddr, STMPE1600_REG_ISGPIOR, tmpData, 2);\n}\n\n/**\n  * @brief  Check if the device instance of the selected address is already registered\n  *         and return its index\n  * @param  DeviceAddr: Device address on communication Bus.\n  * @retval Index of the device instance if registered, 0xFF if not.\n  */\nstatic uint8_t stmpe1600_GetInstance(uint16_t DeviceAddr)\n{\n  uint8_t idx = 0;\n\n  /* Check all the registered instances */\n  for(idx = 0; idx < STMPE1600_MAX_INSTANCE ; idx ++)\n  {\n    /* Return index if there is address match */\n    if(stmpe1600[idx] == DeviceAddr)\n    {\n      return idx;\n    }\n  }\n\n  return 0xFF;\n}\n\n/**\n  * @}\n  */\n\n/**\n  * @}\n  */\n\n/**\n  * @}\n  */\n\n/**\n  * @}\n  */",
      "metadata": {
        "start_line": 501,
        "lang": "c",
        "desc": "Code chunk from EcoflowSTM32F4/lib/bsp/Components/stmpe1600/stmpe1600.c lines 501-584"
      },
      "id": "EcoflowSTM32F4/lib/bsp/Components/stmpe1600/stmpe1600.c:chunk5"
    }
  ]
}